<?xml version="1.0" encoding="utf-8" standalone="no"?>
<resources>
    <string-array name="entries_auto_refresh_content">
        <item>หน้าหลัก</item>
        <item>การโต้ตอบ</item>
        <item>ข้อความส่วนตัว</item>
        <item>เทรนด์</item>
    </string-array>
    <string-array name="entries_compose_now_action">
        <item>เขียน</item>
        <item>ถ่ายรูป</item>
        <item>เพิ่มรูปภาพ</item>
    </string-array>
    <string-array name="entries_home_refresh_content">
        <item>การโต้ตอบ</item>
        <item>ข้อความส่วนตัว</item>
        <item>เทรนด์</item>
        <item>คำค้นที่บันทึกไว้</item>
    </string-array>
    <string-array name="entries_image_sources">
        <item>กล้อง</item>
        <item>คลังภาพ</item>
        <item>คลิปบอร์ด</item>
    </string-array>
    <string-array name="entries_media_preload">
        <item>Wi-Fi</item>
    </string-array>
    <string-array name="entries_media_preview_style">
        <item>ตัด</item>
        <item>สเกล</item>
        <item>ขนาดจริง</item>
    </string-array>
    <string-array name="entries_notification_content">
        <item>หน้าหลัก</item>
        <item>การโต้ตอบ</item>
        <item>ข้อความส่วนตัว</item>
    </string-array>
    <string-array name="entries_profile_image_style">
        <item>กลม</item>
        <item>สี่เหลี่ยม</item>
    </string-array>
    <string-array name="entries_proxy_type">
        <item>HTTP</item>
        <item>พร็อกซีย้อนกลับ</item>
        <!--<item>SOCKS</item>-->
    </string-array>
    <string-array name="entries_quick_access_shortcut_types">
        <item>ผู้ใช้</item>
        <item>ไทม์ไลน์ผู้ใช้</item>
        <item>รายการโปรดของผู้ใช้</item>
        <item>รายการ</item>
        <item>ไทม์ไลน์ของรายการ</item>
    </string-array>
    <string-array name="entries_refresh_interval">
        <item>3 นาที</item>
        <item>5 นาที</item>
        <item>10 นาที</item>
        <item>15 นาที</item>
        <item>30 นาที</item>
        <item>1 ชั่วโมง</item>
        <item>2 ชั่วโมง</item>
        <item>4 ชั่วโมง</item>
    </string-array>
    <string-array name="entries_tab_column_width">
        <item>แคบ</item>
        <item>ปกติ</item>
        <item>กว้าง</item>
    </string-array>
    <string-array name="entries_tab_display_option">
        <item>ไอคอน</item>
        <item>ชื่อ</item>
        <item>ไอคอนและชื่อ</item>
    </string-array>
    <string-array name="entries_theme">
        <item>สว่าง</item>
        <item>มืด</item>
        <item>อัตโนมัติ</item>
    </string-array>
    <string-array name="entries_theme_background">
        <item>ค่าเริ่มต้น</item>
        <item>ขาว/ดำ บริสุทธิ์</item>
        <item>โปร่งใส</item>
    </string-array>
    <string-array name="entries_user_timeline_filter">
        <item>การตอบกลับ</item>
        <item>รีทวีต</item>
    </string-array>
</resources>
